<stg><name>Interface2</name>


<trans_list>

<trans id="52" from="1" to="2">
<condition id="-1">
<or_exp><and_exp></and_exp></or_exp>
</condition>
</trans>

<trans id="54" from="2" to="3">
<condition id="-1">
<or_exp><and_exp></and_exp></or_exp>
</condition>
</trans>
</trans_list>



<state_list>

<state id="1" st_id="1">

<operation id="4" st_id="1" stage="1" lat="1">
<core>NULL</core>
<MemPortIdVec></MemPortIdVec>
<condition id="-1">
<or_exp><and_exp></and_exp></or_exp>
</condition>

<Node id="8" bw="0" op_0_bw="0" op_1_bw="10">
<![CDATA[
:0  call void (...)* @_ssdm_op_SpecBitsMap(i10 %x_V), !map !104

]]></Node>
<StgValue><ssdm name=""/></StgValue>
</operation>

<operation id="5" st_id="1" stage="1" lat="1">
<core>NULL</core>
<MemPortIdVec></MemPortIdVec>
<condition id="-1">
<or_exp><and_exp></and_exp></or_exp>
</condition>

<Node id="9" bw="0" op_0_bw="0" op_1_bw="10">
<![CDATA[
:1  call void (...)* @_ssdm_op_SpecBitsMap(i10 %y_V), !map !110

]]></Node>
<StgValue><ssdm name=""/></StgValue>
</operation>

<operation id="6" st_id="1" stage="1" lat="1">
<core>NULL</core>
<MemPortIdVec></MemPortIdVec>
<condition id="-1">
<or_exp><and_exp></and_exp></or_exp>
</condition>

<Node id="10" bw="0" op_0_bw="0" op_1_bw="8">
<![CDATA[
:2  call void (...)* @_ssdm_op_SpecBitsMap(i8* %XY_Red_V), !map !114

]]></Node>
<StgValue><ssdm name=""/></StgValue>
</operation>

<operation id="7" st_id="1" stage="1" lat="1">
<core>NULL</core>
<MemPortIdVec></MemPortIdVec>
<condition id="-1">
<or_exp><and_exp></and_exp></or_exp>
</condition>

<Node id="11" bw="0" op_0_bw="0" op_1_bw="8">
<![CDATA[
:3  call void (...)* @_ssdm_op_SpecBitsMap(i8* %XY_Green_V), !map !118

]]></Node>
<StgValue><ssdm name=""/></StgValue>
</operation>

<operation id="8" st_id="1" stage="1" lat="1">
<core>NULL</core>
<MemPortIdVec></MemPortIdVec>
<condition id="-1">
<or_exp><and_exp></and_exp></or_exp>
</condition>

<Node id="12" bw="0" op_0_bw="0" op_1_bw="8">
<![CDATA[
:4  call void (...)* @_ssdm_op_SpecBitsMap(i8* %XY_Blue_V), !map !122

]]></Node>
<StgValue><ssdm name=""/></StgValue>
</operation>

<operation id="9" st_id="1" stage="1" lat="1">
<core>NULL</core>
<MemPortIdVec></MemPortIdVec>
<condition id="-1">
<or_exp><and_exp></and_exp></or_exp>
</condition>

<Node id="13" bw="0" op_0_bw="0" op_1_bw="12">
<![CDATA[
:5  call void (...)* @_ssdm_op_SpecBitsMap(i12 %center_line_V), !map !126

]]></Node>
<StgValue><ssdm name=""/></StgValue>
</operation>

<operation id="10" st_id="1" stage="1" lat="1">
<core>NULL</core>
<MemPortIdVec></MemPortIdVec>
<condition id="-1">
<or_exp><and_exp></and_exp></or_exp>
</condition>

<Node id="14" bw="0" op_0_bw="0" op_1_bw="1">
<![CDATA[
:6  call void (...)* @_ssdm_op_SpecBitsMap(i1 %right_r), !map !130

]]></Node>
<StgValue><ssdm name=""/></StgValue>
</operation>

<operation id="11" st_id="1" stage="1" lat="1">
<core>NULL</core>
<MemPortIdVec></MemPortIdVec>
<condition id="-1">
<or_exp><and_exp></and_exp></or_exp>
</condition>

<Node id="15" bw="0" op_0_bw="0" op_1_bw="0">
<![CDATA[
:7  call void (...)* @_ssdm_op_SpecTopModule([11 x i8]* @Interface2_str) nounwind

]]></Node>
<StgValue><ssdm name=""/></StgValue>
</operation>

<operation id="12" st_id="1" stage="1" lat="1">
<core>NULL</core>
<MemPortIdVec></MemPortIdVec>
<condition id="-1">
<or_exp><and_exp></and_exp></or_exp>
</condition>

<Node id="16" bw="1" op_0_bw="1" op_1_bw="1">
<![CDATA[
:8  %right_read = call i1 @_ssdm_op_Read.ap_auto.i1(i1 %right_r)

]]></Node>
<StgValue><ssdm name="right_read"/></StgValue>
</operation>

<operation id="13" st_id="1" stage="1" lat="1">
<core>NULL</core>
<MemPortIdVec></MemPortIdVec>
<condition id="-1">
<or_exp><and_exp></and_exp></or_exp>
</condition>

<Node id="17" bw="12" op_0_bw="12" op_1_bw="12">
<![CDATA[
:9  %center_line_V_read = call i12 @_ssdm_op_Read.ap_none.i12(i12 %center_line_V)

]]></Node>
<StgValue><ssdm name="center_line_V_read"/></StgValue>
</operation>

<operation id="14" st_id="1" stage="1" lat="1">
<core>NULL</core>
<MemPortIdVec></MemPortIdVec>
<condition id="-1">
<or_exp><and_exp></and_exp></or_exp>
</condition>

<Node id="18" bw="10" op_0_bw="10" op_1_bw="10">
<![CDATA[
:10  %y_V_read = call i10 @_ssdm_op_Read.ap_none.i10(i10 %y_V)

]]></Node>
<StgValue><ssdm name="y_V_read"/></StgValue>
</operation>

<operation id="15" st_id="1" stage="1" lat="1">
<core>NULL</core>
<MemPortIdVec></MemPortIdVec>
<condition id="-1">
<or_exp><and_exp></and_exp></or_exp>
</condition>

<Node id="19" bw="10" op_0_bw="10" op_1_bw="10">
<![CDATA[
:11  %x_V_read = call i10 @_ssdm_op_Read.ap_none.i10(i10 %x_V)

]]></Node>
<StgValue><ssdm name="x_V_read"/></StgValue>
</operation>

<operation id="16" st_id="1" stage="1" lat="1">
<core>NULL</core>
<MemPortIdVec></MemPortIdVec>
<condition id="-1">
<or_exp><and_exp></and_exp></or_exp>
</condition>

<Node id="20" bw="0" op_0_bw="0" op_1_bw="10" op_2_bw="0" op_3_bw="32" op_4_bw="32" op_5_bw="0" op_6_bw="32" op_7_bw="32" op_8_bw="0" op_9_bw="0" op_10_bw="0" op_11_bw="32" op_12_bw="32" op_13_bw="32" op_14_bw="32" op_15_bw="0" op_16_bw="0">
<![CDATA[
:12  call void (...)* @_ssdm_op_SpecInterface(i10 %x_V, [8 x i8]* @p_str2, i32 0, i32 0, [1 x i8]* @p_str, i32 0, i32 0, [1 x i8]* @p_str, [1 x i8]* @p_str, [1 x i8]* @p_str, i32 0, i32 0, i32 0, i32 0, [1 x i8]* @p_str, [1 x i8]* @p_str) nounwind

]]></Node>
<StgValue><ssdm name=""/></StgValue>
</operation>

<operation id="17" st_id="1" stage="1" lat="1">
<core>NULL</core>
<MemPortIdVec></MemPortIdVec>
<condition id="-1">
<or_exp><and_exp></and_exp></or_exp>
</condition>

<Node id="21" bw="0" op_0_bw="0" op_1_bw="10" op_2_bw="0" op_3_bw="32" op_4_bw="32" op_5_bw="0" op_6_bw="32" op_7_bw="32" op_8_bw="0" op_9_bw="0" op_10_bw="0" op_11_bw="32" op_12_bw="32" op_13_bw="32" op_14_bw="32" op_15_bw="0" op_16_bw="0">
<![CDATA[
:13  call void (...)* @_ssdm_op_SpecInterface(i10 %y_V, [8 x i8]* @p_str2, i32 0, i32 0, [1 x i8]* @p_str, i32 0, i32 0, [1 x i8]* @p_str, [1 x i8]* @p_str, [1 x i8]* @p_str, i32 0, i32 0, i32 0, i32 0, [1 x i8]* @p_str, [1 x i8]* @p_str) nounwind

]]></Node>
<StgValue><ssdm name=""/></StgValue>
</operation>

<operation id="18" st_id="1" stage="1" lat="1">
<core>NULL</core>
<MemPortIdVec></MemPortIdVec>
<condition id="-1">
<or_exp><and_exp></and_exp></or_exp>
</condition>

<Node id="22" bw="0" op_0_bw="0" op_1_bw="8" op_2_bw="0" op_3_bw="32" op_4_bw="32" op_5_bw="0" op_6_bw="32" op_7_bw="32" op_8_bw="0" op_9_bw="0" op_10_bw="0" op_11_bw="32" op_12_bw="32" op_13_bw="32" op_14_bw="32" op_15_bw="0" op_16_bw="0">
<![CDATA[
:14  call void (...)* @_ssdm_op_SpecInterface(i8* %XY_Red_V, [8 x i8]* @p_str2, i32 0, i32 0, [1 x i8]* @p_str, i32 0, i32 0, [1 x i8]* @p_str, [1 x i8]* @p_str, [1 x i8]* @p_str, i32 0, i32 0, i32 0, i32 0, [1 x i8]* @p_str, [1 x i8]* @p_str) nounwind

]]></Node>
<StgValue><ssdm name=""/></StgValue>
</operation>

<operation id="19" st_id="1" stage="1" lat="1">
<core>NULL</core>
<MemPortIdVec></MemPortIdVec>
<condition id="-1">
<or_exp><and_exp></and_exp></or_exp>
</condition>

<Node id="23" bw="0" op_0_bw="0" op_1_bw="8" op_2_bw="0" op_3_bw="32" op_4_bw="32" op_5_bw="0" op_6_bw="32" op_7_bw="32" op_8_bw="0" op_9_bw="0" op_10_bw="0" op_11_bw="32" op_12_bw="32" op_13_bw="32" op_14_bw="32" op_15_bw="0" op_16_bw="0">
<![CDATA[
:15  call void (...)* @_ssdm_op_SpecInterface(i8* %XY_Green_V, [8 x i8]* @p_str2, i32 0, i32 0, [1 x i8]* @p_str, i32 0, i32 0, [1 x i8]* @p_str, [1 x i8]* @p_str, [1 x i8]* @p_str, i32 0, i32 0, i32 0, i32 0, [1 x i8]* @p_str, [1 x i8]* @p_str) nounwind

]]></Node>
<StgValue><ssdm name=""/></StgValue>
</operation>

<operation id="20" st_id="1" stage="1" lat="1">
<core>NULL</core>
<MemPortIdVec></MemPortIdVec>
<condition id="-1">
<or_exp><and_exp></and_exp></or_exp>
</condition>

<Node id="24" bw="0" op_0_bw="0" op_1_bw="8" op_2_bw="0" op_3_bw="32" op_4_bw="32" op_5_bw="0" op_6_bw="32" op_7_bw="32" op_8_bw="0" op_9_bw="0" op_10_bw="0" op_11_bw="32" op_12_bw="32" op_13_bw="32" op_14_bw="32" op_15_bw="0" op_16_bw="0">
<![CDATA[
:16  call void (...)* @_ssdm_op_SpecInterface(i8* %XY_Blue_V, [8 x i8]* @p_str2, i32 0, i32 0, [1 x i8]* @p_str, i32 0, i32 0, [1 x i8]* @p_str, [1 x i8]* @p_str, [1 x i8]* @p_str, i32 0, i32 0, i32 0, i32 0, [1 x i8]* @p_str, [1 x i8]* @p_str) nounwind

]]></Node>
<StgValue><ssdm name=""/></StgValue>
</operation>

<operation id="21" st_id="1" stage="1" lat="1">
<core>NULL</core>
<MemPortIdVec></MemPortIdVec>
<condition id="-1">
<or_exp><and_exp></and_exp></or_exp>
</condition>

<Node id="25" bw="0" op_0_bw="0" op_1_bw="12" op_2_bw="0" op_3_bw="32" op_4_bw="32" op_5_bw="0" op_6_bw="32" op_7_bw="32" op_8_bw="0" op_9_bw="0" op_10_bw="0" op_11_bw="32" op_12_bw="32" op_13_bw="32" op_14_bw="32" op_15_bw="0" op_16_bw="0">
<![CDATA[
:17  call void (...)* @_ssdm_op_SpecInterface(i12 %center_line_V, [8 x i8]* @p_str2, i32 0, i32 0, [1 x i8]* @p_str, i32 0, i32 0, [1 x i8]* @p_str, [1 x i8]* @p_str, [1 x i8]* @p_str, i32 0, i32 0, i32 0, i32 0, [1 x i8]* @p_str, [1 x i8]* @p_str) nounwind

]]></Node>
<StgValue><ssdm name=""/></StgValue>
</operation>

<operation id="22" st_id="1" stage="1" lat="1">
<core>Cmp</core>
<MemPortIdVec></MemPortIdVec>
<condition id="-1">
<or_exp><and_exp></and_exp></or_exp>
</condition>

<Node id="26" bw="1" op_0_bw="10" op_1_bw="10">
<![CDATA[
:18  %tmp = icmp ult i10 %y_V_read, 40

]]></Node>
<StgValue><ssdm name="tmp"/></StgValue>
</operation>

<operation id="23" st_id="1" stage="1" lat="1">
<core>NULL</core>
<MemPortIdVec></MemPortIdVec>
<condition id="-1">
<or_exp><and_exp></and_exp></or_exp>
</condition>

<Node id="27" bw="0" op_0_bw="1" op_1_bw="0" op_2_bw="0">
<![CDATA[
:19  br i1 %tmp, label %1, label %._crit_edge.i

]]></Node>
<StgValue><ssdm name=""/></StgValue>
</operation>

<operation id="24" st_id="1" stage="1" lat="1">
<core>Cmp</core>
<MemPortIdVec></MemPortIdVec>
<condition id="-1">
<or_exp><and_exp><literal name="tmp" val="1"/>
</and_exp></or_exp>
</condition>

<Node id="29" bw="1" op_0_bw="10" op_1_bw="10">
<![CDATA[
:0  %tmp_1 = icmp ult i10 %x_V_read, 320

]]></Node>
<StgValue><ssdm name="tmp_1"/></StgValue>
</operation>

<operation id="25" st_id="1" stage="1" lat="1">
<core>NULL</core>
<MemPortIdVec></MemPortIdVec>
<condition id="-1">
<or_exp><and_exp><literal name="tmp" val="1"/>
</and_exp></or_exp>
</condition>

<Node id="30" bw="0" op_0_bw="1" op_1_bw="0" op_2_bw="0">
<![CDATA[
:1  br i1 %tmp_1, label %2, label %._crit_edge185.i

]]></Node>
<StgValue><ssdm name=""/></StgValue>
</operation>

<operation id="26" st_id="1" stage="1" lat="1">
<core>LogicGate</core>
<MemPortIdVec></MemPortIdVec>
<condition id="-1">
<or_exp><and_exp><literal name="tmp" val="1"/>
<literal name="tmp_1" val="1"/>
</and_exp></or_exp>
</condition>

<Node id="32" bw="1" op_0_bw="1" op_1_bw="1">
<![CDATA[
:0  %not_right = xor i1 %right_read, true

]]></Node>
<StgValue><ssdm name="not_right"/></StgValue>
</operation>

<operation id="27" st_id="1" stage="1" lat="1">
<core>Sel</core>
<MemPortIdVec></MemPortIdVec>
<condition id="-1">
<or_exp><and_exp><literal name="tmp" val="1"/>
<literal name="tmp_1" val="1"/>
</and_exp></or_exp>
</condition>

<Node id="33" bw="8" op_0_bw="1" op_1_bw="8" op_2_bw="8">
<![CDATA[
:1  %storemerge7_cast = select i1 %not_right, i8 -1, i8 0

]]></Node>
<StgValue><ssdm name="storemerge7_cast"/></StgValue>
</operation>

<operation id="28" st_id="1" stage="1" lat="1">
<core>NULL</core>
<MemPortIdVec></MemPortIdVec>
<condition id="-1">
<or_exp><and_exp><literal name="tmp" val="1"/>
<literal name="tmp_1" val="1"/>
</and_exp></or_exp>
</condition>

<Node id="34" bw="0" op_0_bw="0" op_1_bw="8" op_2_bw="8">
<![CDATA[
:2  call void @_ssdm_op_Write.ap_none.i8P(i8* %XY_Red_V, i8 %storemerge7_cast)

]]></Node>
<StgValue><ssdm name=""/></StgValue>
</operation>

<operation id="29" st_id="1" stage="1" lat="1">
<core>NULL</core>
<MemPortIdVec></MemPortIdVec>
<condition id="-1">
<or_exp><and_exp><literal name="tmp" val="1"/>
<literal name="tmp_1" val="1"/>
</and_exp></or_exp>
</condition>

<Node id="35" bw="0" op_0_bw="0" op_1_bw="8" op_2_bw="8">
<![CDATA[
:3  call void @_ssdm_op_Write.ap_none.i8P(i8* %XY_Blue_V, i8 %storemerge7_cast)

]]></Node>
<StgValue><ssdm name=""/></StgValue>
</operation>

<operation id="30" st_id="1" stage="1" lat="1">
<core>NULL</core>
<MemPortIdVec></MemPortIdVec>
<condition id="-1">
<or_exp><and_exp><literal name="tmp" val="1"/>
<literal name="tmp_1" val="1"/>
</and_exp></or_exp>
</condition>

<Node id="36" bw="0" op_0_bw="0" op_1_bw="8" op_2_bw="8">
<![CDATA[
:4  call void @_ssdm_op_Write.ap_none.i8P(i8* %XY_Green_V, i8 %storemerge7_cast)

]]></Node>
<StgValue><ssdm name=""/></StgValue>
</operation>

<operation id="31" st_id="1" stage="1" lat="1">
<core>NULL</core>
<MemPortIdVec></MemPortIdVec>
<condition id="-1">
<or_exp><and_exp><literal name="tmp" val="1"/>
<literal name="tmp_1" val="1"/>
</and_exp></or_exp>
</condition>

<Node id="37" bw="0" op_0_bw="0">
<![CDATA[
:5  br label %._crit_edge185.i

]]></Node>
<StgValue><ssdm name=""/></StgValue>
</operation>

<operation id="32" st_id="1" stage="1" lat="1">
<core>Cmp</core>
<MemPortIdVec></MemPortIdVec>
<condition id="-1">
<or_exp><and_exp><literal name="tmp" val="1"/>
</and_exp></or_exp>
</condition>

<Node id="39" bw="1" op_0_bw="10" op_1_bw="10">
<![CDATA[
._crit_edge185.i:0  %tmp_2 = icmp ugt i10 %x_V_read, 320

]]></Node>
<StgValue><ssdm name="tmp_2"/></StgValue>
</operation>

<operation id="33" st_id="1" stage="1" lat="1">
<core>NULL</core>
<MemPortIdVec></MemPortIdVec>
<condition id="-1">
<or_exp><and_exp><literal name="tmp" val="1"/>
</and_exp></or_exp>
</condition>

<Node id="40" bw="0" op_0_bw="1" op_1_bw="0" op_2_bw="0">
<![CDATA[
._crit_edge185.i:1  br i1 %tmp_2, label %3, label %._crit_edge186.i

]]></Node>
<StgValue><ssdm name=""/></StgValue>
</operation>
</state>

<state id="2" st_id="2">

<operation id="34" st_id="2" stage="1" lat="1">
<core>Sel</core>
<MemPortIdVec></MemPortIdVec>
<condition id="-1">
<or_exp><and_exp><literal name="tmp" val="1"/>
<literal name="tmp_2" val="1"/>
</and_exp></or_exp>
</condition>

<Node id="42" bw="8" op_0_bw="1" op_1_bw="8" op_2_bw="8">
<![CDATA[
:0  %storemerge6 = select i1 %right_read, i8 -1, i8 0

]]></Node>
<StgValue><ssdm name="storemerge6"/></StgValue>
</operation>

<operation id="35" st_id="2" stage="1" lat="1">
<core>NULL</core>
<MemPortIdVec></MemPortIdVec>
<condition id="-1">
<or_exp><and_exp><literal name="tmp" val="1"/>
<literal name="tmp_2" val="1"/>
</and_exp></or_exp>
</condition>

<Node id="43" bw="0" op_0_bw="0" op_1_bw="8" op_2_bw="8">
<![CDATA[
:1  call void @_ssdm_op_Write.ap_none.i8P(i8* %XY_Red_V, i8 %storemerge6)

]]></Node>
<StgValue><ssdm name=""/></StgValue>
</operation>

<operation id="36" st_id="2" stage="1" lat="1">
<core>NULL</core>
<MemPortIdVec></MemPortIdVec>
<condition id="-1">
<or_exp><and_exp><literal name="tmp" val="1"/>
<literal name="tmp_2" val="1"/>
</and_exp></or_exp>
</condition>

<Node id="44" bw="0" op_0_bw="0" op_1_bw="8" op_2_bw="8">
<![CDATA[
:2  call void @_ssdm_op_Write.ap_none.i8P(i8* %XY_Blue_V, i8 %storemerge6)

]]></Node>
<StgValue><ssdm name=""/></StgValue>
</operation>

<operation id="37" st_id="2" stage="1" lat="1">
<core>NULL</core>
<MemPortIdVec></MemPortIdVec>
<condition id="-1">
<or_exp><and_exp><literal name="tmp" val="1"/>
<literal name="tmp_2" val="1"/>
</and_exp></or_exp>
</condition>

<Node id="45" bw="0" op_0_bw="0" op_1_bw="8" op_2_bw="8">
<![CDATA[
:3  call void @_ssdm_op_Write.ap_none.i8P(i8* %XY_Green_V, i8 %storemerge6)

]]></Node>
<StgValue><ssdm name=""/></StgValue>
</operation>

<operation id="38" st_id="2" stage="1" lat="1">
<core>NULL</core>
<MemPortIdVec></MemPortIdVec>
<condition id="-1">
<or_exp><and_exp><literal name="tmp" val="1"/>
<literal name="tmp_2" val="1"/>
</and_exp></or_exp>
</condition>

<Node id="46" bw="0" op_0_bw="0">
<![CDATA[
:4  br label %._crit_edge186.i

]]></Node>
<StgValue><ssdm name=""/></StgValue>
</operation>

<operation id="39" st_id="2" stage="1" lat="1">
<core>NULL</core>
<MemPortIdVec></MemPortIdVec>
<condition id="-1">
<or_exp><and_exp><literal name="tmp" val="1"/>
</and_exp></or_exp>
</condition>

<Node id="48" bw="0" op_0_bw="0">
<![CDATA[
._crit_edge186.i:0  br label %._crit_edge.i

]]></Node>
<StgValue><ssdm name=""/></StgValue>
</operation>

<operation id="40" st_id="2" stage="1" lat="1">
<core>Cmp</core>
<MemPortIdVec></MemPortIdVec>
<condition id="-1">
<or_exp><and_exp></and_exp></or_exp>
</condition>

<Node id="50" bw="1" op_0_bw="10" op_1_bw="10">
<![CDATA[
._crit_edge.i:0  %tmp_3 = icmp ugt i10 %y_V_read, 40

]]></Node>
<StgValue><ssdm name="tmp_3"/></StgValue>
</operation>

<operation id="41" st_id="2" stage="1" lat="1">
<core>NULL</core>
<MemPortIdVec></MemPortIdVec>
<condition id="-1">
<or_exp><and_exp></and_exp></or_exp>
</condition>

<Node id="51" bw="0" op_0_bw="1" op_1_bw="0" op_2_bw="0">
<![CDATA[
._crit_edge.i:1  br i1 %tmp_3, label %4, label %retBit.exit

]]></Node>
<StgValue><ssdm name=""/></StgValue>
</operation>

<operation id="42" st_id="2" stage="1" lat="1">
<core>NULL</core>
<MemPortIdVec></MemPortIdVec>
<condition id="-1">
<or_exp><and_exp><literal name="tmp_3" val="1"/>
</and_exp></or_exp>
</condition>

<Node id="53" bw="12" op_0_bw="10">
<![CDATA[
:0  %tmp_4_cast = zext i10 %x_V_read to i12

]]></Node>
<StgValue><ssdm name="tmp_4_cast"/></StgValue>
</operation>

<operation id="43" st_id="2" stage="1" lat="1">
<core>Cmp</core>
<MemPortIdVec></MemPortIdVec>
<condition id="-1">
<or_exp><and_exp><literal name="tmp_3" val="1"/>
</and_exp></or_exp>
</condition>

<Node id="54" bw="1" op_0_bw="12" op_1_bw="12">
<![CDATA[
:1  %tmp_6 = icmp ugt i12 %tmp_4_cast, %center_line_V_read

]]></Node>
<StgValue><ssdm name="tmp_6"/></StgValue>
</operation>
</state>

<state id="3" st_id="3">

<operation id="44" st_id="3" stage="1" lat="1">
<core>LogicGate</core>
<MemPortIdVec></MemPortIdVec>
<condition id="-1">
<or_exp><and_exp><literal name="tmp_3" val="1"/>
</and_exp></or_exp>
</condition>

<Node id="55" bw="1" op_0_bw="1" op_1_bw="1">
<![CDATA[
:2  %not_tmp_6 = xor i1 %tmp_6, true

]]></Node>
<StgValue><ssdm name="not_tmp_6"/></StgValue>
</operation>

<operation id="45" st_id="3" stage="1" lat="1">
<core>Sel</core>
<MemPortIdVec></MemPortIdVec>
<condition id="-1">
<or_exp><and_exp><literal name="tmp_3" val="1"/>
</and_exp></or_exp>
</condition>

<Node id="56" bw="8" op_0_bw="1" op_1_bw="8" op_2_bw="8">
<![CDATA[
:3  %storemerge5_cast = select i1 %not_tmp_6, i8 -1, i8 0

]]></Node>
<StgValue><ssdm name="storemerge5_cast"/></StgValue>
</operation>

<operation id="46" st_id="3" stage="1" lat="1">
<core>Sel</core>
<MemPortIdVec></MemPortIdVec>
<condition id="-1">
<or_exp><and_exp><literal name="tmp_3" val="1"/>
</and_exp></or_exp>
</condition>

<Node id="57" bw="8" op_0_bw="1" op_1_bw="8" op_2_bw="8">
<![CDATA[
:4  %storemerge = select i1 %tmp_6, i8 -1, i8 0

]]></Node>
<StgValue><ssdm name="storemerge"/></StgValue>
</operation>

<operation id="47" st_id="3" stage="1" lat="1">
<core>NULL</core>
<MemPortIdVec></MemPortIdVec>
<condition id="-1">
<or_exp><and_exp><literal name="tmp_3" val="1"/>
</and_exp></or_exp>
</condition>

<Node id="58" bw="0" op_0_bw="0" op_1_bw="8" op_2_bw="8">
<![CDATA[
:5  call void @_ssdm_op_Write.ap_none.i8P(i8* %XY_Red_V, i8 %storemerge5_cast)

]]></Node>
<StgValue><ssdm name=""/></StgValue>
</operation>

<operation id="48" st_id="3" stage="1" lat="1">
<core>NULL</core>
<MemPortIdVec></MemPortIdVec>
<condition id="-1">
<or_exp><and_exp><literal name="tmp_3" val="1"/>
</and_exp></or_exp>
</condition>

<Node id="59" bw="0" op_0_bw="0" op_1_bw="8" op_2_bw="8">
<![CDATA[
:6  call void @_ssdm_op_Write.ap_none.i8P(i8* %XY_Blue_V, i8 0)

]]></Node>
<StgValue><ssdm name=""/></StgValue>
</operation>

<operation id="49" st_id="3" stage="1" lat="1">
<core>NULL</core>
<MemPortIdVec></MemPortIdVec>
<condition id="-1">
<or_exp><and_exp><literal name="tmp_3" val="1"/>
</and_exp></or_exp>
</condition>

<Node id="60" bw="0" op_0_bw="0" op_1_bw="8" op_2_bw="8">
<![CDATA[
:7  call void @_ssdm_op_Write.ap_none.i8P(i8* %XY_Green_V, i8 %storemerge)

]]></Node>
<StgValue><ssdm name=""/></StgValue>
</operation>

<operation id="50" st_id="3" stage="1" lat="1">
<core>NULL</core>
<MemPortIdVec></MemPortIdVec>
<condition id="-1">
<or_exp><and_exp><literal name="tmp_3" val="1"/>
</and_exp></or_exp>
</condition>

<Node id="61" bw="0" op_0_bw="0">
<![CDATA[
:8  br label %retBit.exit

]]></Node>
<StgValue><ssdm name=""/></StgValue>
</operation>

<operation id="51" st_id="3" stage="1" lat="1">
<core>NULL</core>
<MemPortIdVec></MemPortIdVec>
<condition id="-1">
<or_exp><and_exp></and_exp></or_exp>
</condition>

<Node id="63" bw="0">
<![CDATA[
retBit.exit:0  ret void

]]></Node>
<StgValue><ssdm name=""/></StgValue>
</operation>
</state>
</state_list>


<ports>
<port id="56" name="x_V" dir="0" iftype="0">
<core>NULL</core><StgValue><ssdm name="x_V"/></StgValue>
</port>
<port id="57" name="y_V" dir="0" iftype="0">
<core>NULL</core><StgValue><ssdm name="y_V"/></StgValue>
</port>
<port id="58" name="XY_Red_V" dir="1" iftype="0">
<core>NULL</core><StgValue><ssdm name="XY_Red_V"/></StgValue>
</port>
<port id="59" name="XY_Green_V" dir="1" iftype="0">
<core>NULL</core><StgValue><ssdm name="XY_Green_V"/></StgValue>
</port>
<port id="60" name="XY_Blue_V" dir="1" iftype="0">
<core>NULL</core><StgValue><ssdm name="XY_Blue_V"/></StgValue>
</port>
<port id="61" name="center_line_V" dir="0" iftype="0">
<core>NULL</core><StgValue><ssdm name="center_line_V"/></StgValue>
</port>
<port id="62" name="right_r" dir="0" iftype="0">
<core>NULL</core><StgValue><ssdm name="right_r"/></StgValue>
</port>
</ports>


<dataflows>
<dataflow id="64" from="_ssdm_op_SpecBitsMap" to="StgValue_4" fromId="63" toId="4">
</dataflow>
<dataflow id="65" from="x_V" to="StgValue_4" fromId="56" toId="4">
</dataflow>
<dataflow id="66" from="_ssdm_op_SpecBitsMap" to="StgValue_5" fromId="63" toId="5">
</dataflow>
<dataflow id="67" from="y_V" to="StgValue_5" fromId="57" toId="5">
</dataflow>
<dataflow id="68" from="_ssdm_op_SpecBitsMap" to="StgValue_6" fromId="63" toId="6">
</dataflow>
<dataflow id="69" from="XY_Red_V" to="StgValue_6" fromId="58" toId="6">
</dataflow>
<dataflow id="70" from="_ssdm_op_SpecBitsMap" to="StgValue_7" fromId="63" toId="7">
</dataflow>
<dataflow id="71" from="XY_Green_V" to="StgValue_7" fromId="59" toId="7">
</dataflow>
<dataflow id="72" from="_ssdm_op_SpecBitsMap" to="StgValue_8" fromId="63" toId="8">
</dataflow>
<dataflow id="73" from="XY_Blue_V" to="StgValue_8" fromId="60" toId="8">
</dataflow>
<dataflow id="74" from="_ssdm_op_SpecBitsMap" to="StgValue_9" fromId="63" toId="9">
</dataflow>
<dataflow id="75" from="center_line_V" to="StgValue_9" fromId="61" toId="9">
</dataflow>
<dataflow id="76" from="_ssdm_op_SpecBitsMap" to="StgValue_10" fromId="63" toId="10">
</dataflow>
<dataflow id="77" from="right_r" to="StgValue_10" fromId="62" toId="10">
</dataflow>
<dataflow id="79" from="_ssdm_op_SpecTopModule" to="StgValue_11" fromId="78" toId="11">
</dataflow>
<dataflow id="81" from="Interface2_str" to="StgValue_11" fromId="80" toId="11">
</dataflow>
<dataflow id="83" from="_ssdm_op_Read.ap_auto.i1" to="right_read" fromId="82" toId="12">
</dataflow>
<dataflow id="84" from="right_r" to="right_read" fromId="62" toId="12">
</dataflow>
<dataflow id="86" from="_ssdm_op_Read.ap_none.i12" to="center_line_V_read" fromId="85" toId="13">
</dataflow>
<dataflow id="87" from="center_line_V" to="center_line_V_read" fromId="61" toId="13">
</dataflow>
<dataflow id="89" from="_ssdm_op_Read.ap_none.i10" to="y_V_read" fromId="88" toId="14">
</dataflow>
<dataflow id="90" from="y_V" to="y_V_read" fromId="57" toId="14">
</dataflow>
<dataflow id="91" from="_ssdm_op_Read.ap_none.i10" to="x_V_read" fromId="88" toId="15">
</dataflow>
<dataflow id="92" from="x_V" to="x_V_read" fromId="56" toId="15">
</dataflow>
<dataflow id="94" from="_ssdm_op_SpecInterface" to="StgValue_16" fromId="93" toId="16">
</dataflow>
<dataflow id="95" from="x_V" to="StgValue_16" fromId="56" toId="16">
</dataflow>
<dataflow id="97" from="p_str2" to="StgValue_16" fromId="96" toId="16">
</dataflow>
<dataflow id="99" from="StgValue_98" to="StgValue_16" fromId="98" toId="16">
</dataflow>
<dataflow id="100" from="StgValue_98" to="StgValue_16" fromId="98" toId="16">
</dataflow>
<dataflow id="102" from="p_str" to="StgValue_16" fromId="101" toId="16">
</dataflow>
<dataflow id="103" from="StgValue_98" to="StgValue_16" fromId="98" toId="16">
</dataflow>
<dataflow id="104" from="StgValue_98" to="StgValue_16" fromId="98" toId="16">
</dataflow>
<dataflow id="105" from="p_str" to="StgValue_16" fromId="101" toId="16">
</dataflow>
<dataflow id="106" from="p_str" to="StgValue_16" fromId="101" toId="16">
</dataflow>
<dataflow id="107" from="p_str" to="StgValue_16" fromId="101" toId="16">
</dataflow>
<dataflow id="108" from="StgValue_98" to="StgValue_16" fromId="98" toId="16">
</dataflow>
<dataflow id="109" from="StgValue_98" to="StgValue_16" fromId="98" toId="16">
</dataflow>
<dataflow id="110" from="StgValue_98" to="StgValue_16" fromId="98" toId="16">
</dataflow>
<dataflow id="111" from="StgValue_98" to="StgValue_16" fromId="98" toId="16">
</dataflow>
<dataflow id="112" from="p_str" to="StgValue_16" fromId="101" toId="16">
</dataflow>
<dataflow id="113" from="p_str" to="StgValue_16" fromId="101" toId="16">
</dataflow>
<dataflow id="114" from="_ssdm_op_SpecInterface" to="StgValue_17" fromId="93" toId="17">
</dataflow>
<dataflow id="115" from="y_V" to="StgValue_17" fromId="57" toId="17">
</dataflow>
<dataflow id="116" from="p_str2" to="StgValue_17" fromId="96" toId="17">
</dataflow>
<dataflow id="117" from="StgValue_98" to="StgValue_17" fromId="98" toId="17">
</dataflow>
<dataflow id="118" from="StgValue_98" to="StgValue_17" fromId="98" toId="17">
</dataflow>
<dataflow id="119" from="p_str" to="StgValue_17" fromId="101" toId="17">
</dataflow>
<dataflow id="120" from="StgValue_98" to="StgValue_17" fromId="98" toId="17">
</dataflow>
<dataflow id="121" from="StgValue_98" to="StgValue_17" fromId="98" toId="17">
</dataflow>
<dataflow id="122" from="p_str" to="StgValue_17" fromId="101" toId="17">
</dataflow>
<dataflow id="123" from="p_str" to="StgValue_17" fromId="101" toId="17">
</dataflow>
<dataflow id="124" from="p_str" to="StgValue_17" fromId="101" toId="17">
</dataflow>
<dataflow id="125" from="StgValue_98" to="StgValue_17" fromId="98" toId="17">
</dataflow>
<dataflow id="126" from="StgValue_98" to="StgValue_17" fromId="98" toId="17">
</dataflow>
<dataflow id="127" from="StgValue_98" to="StgValue_17" fromId="98" toId="17">
</dataflow>
<dataflow id="128" from="StgValue_98" to="StgValue_17" fromId="98" toId="17">
</dataflow>
<dataflow id="129" from="p_str" to="StgValue_17" fromId="101" toId="17">
</dataflow>
<dataflow id="130" from="p_str" to="StgValue_17" fromId="101" toId="17">
</dataflow>
<dataflow id="131" from="_ssdm_op_SpecInterface" to="StgValue_18" fromId="93" toId="18">
</dataflow>
<dataflow id="132" from="XY_Red_V" to="StgValue_18" fromId="58" toId="18">
</dataflow>
<dataflow id="133" from="p_str2" to="StgValue_18" fromId="96" toId="18">
</dataflow>
<dataflow id="134" from="StgValue_98" to="StgValue_18" fromId="98" toId="18">
</dataflow>
<dataflow id="135" from="StgValue_98" to="StgValue_18" fromId="98" toId="18">
</dataflow>
<dataflow id="136" from="p_str" to="StgValue_18" fromId="101" toId="18">
</dataflow>
<dataflow id="137" from="StgValue_98" to="StgValue_18" fromId="98" toId="18">
</dataflow>
<dataflow id="138" from="StgValue_98" to="StgValue_18" fromId="98" toId="18">
</dataflow>
<dataflow id="139" from="p_str" to="StgValue_18" fromId="101" toId="18">
</dataflow>
<dataflow id="140" from="p_str" to="StgValue_18" fromId="101" toId="18">
</dataflow>
<dataflow id="141" from="p_str" to="StgValue_18" fromId="101" toId="18">
</dataflow>
<dataflow id="142" from="StgValue_98" to="StgValue_18" fromId="98" toId="18">
</dataflow>
<dataflow id="143" from="StgValue_98" to="StgValue_18" fromId="98" toId="18">
</dataflow>
<dataflow id="144" from="StgValue_98" to="StgValue_18" fromId="98" toId="18">
</dataflow>
<dataflow id="145" from="StgValue_98" to="StgValue_18" fromId="98" toId="18">
</dataflow>
<dataflow id="146" from="p_str" to="StgValue_18" fromId="101" toId="18">
</dataflow>
<dataflow id="147" from="p_str" to="StgValue_18" fromId="101" toId="18">
</dataflow>
<dataflow id="148" from="_ssdm_op_SpecInterface" to="StgValue_19" fromId="93" toId="19">
</dataflow>
<dataflow id="149" from="XY_Green_V" to="StgValue_19" fromId="59" toId="19">
</dataflow>
<dataflow id="150" from="p_str2" to="StgValue_19" fromId="96" toId="19">
</dataflow>
<dataflow id="151" from="StgValue_98" to="StgValue_19" fromId="98" toId="19">
</dataflow>
<dataflow id="152" from="StgValue_98" to="StgValue_19" fromId="98" toId="19">
</dataflow>
<dataflow id="153" from="p_str" to="StgValue_19" fromId="101" toId="19">
</dataflow>
<dataflow id="154" from="StgValue_98" to="StgValue_19" fromId="98" toId="19">
</dataflow>
<dataflow id="155" from="StgValue_98" to="StgValue_19" fromId="98" toId="19">
</dataflow>
<dataflow id="156" from="p_str" to="StgValue_19" fromId="101" toId="19">
</dataflow>
<dataflow id="157" from="p_str" to="StgValue_19" fromId="101" toId="19">
</dataflow>
<dataflow id="158" from="p_str" to="StgValue_19" fromId="101" toId="19">
</dataflow>
<dataflow id="159" from="StgValue_98" to="StgValue_19" fromId="98" toId="19">
</dataflow>
<dataflow id="160" from="StgValue_98" to="StgValue_19" fromId="98" toId="19">
</dataflow>
<dataflow id="161" from="StgValue_98" to="StgValue_19" fromId="98" toId="19">
</dataflow>
<dataflow id="162" from="StgValue_98" to="StgValue_19" fromId="98" toId="19">
</dataflow>
<dataflow id="163" from="p_str" to="StgValue_19" fromId="101" toId="19">
</dataflow>
<dataflow id="164" from="p_str" to="StgValue_19" fromId="101" toId="19">
</dataflow>
<dataflow id="165" from="_ssdm_op_SpecInterface" to="StgValue_20" fromId="93" toId="20">
</dataflow>
<dataflow id="166" from="XY_Blue_V" to="StgValue_20" fromId="60" toId="20">
</dataflow>
<dataflow id="167" from="p_str2" to="StgValue_20" fromId="96" toId="20">
</dataflow>
<dataflow id="168" from="StgValue_98" to="StgValue_20" fromId="98" toId="20">
</dataflow>
<dataflow id="169" from="StgValue_98" to="StgValue_20" fromId="98" toId="20">
</dataflow>
<dataflow id="170" from="p_str" to="StgValue_20" fromId="101" toId="20">
</dataflow>
<dataflow id="171" from="StgValue_98" to="StgValue_20" fromId="98" toId="20">
</dataflow>
<dataflow id="172" from="StgValue_98" to="StgValue_20" fromId="98" toId="20">
</dataflow>
<dataflow id="173" from="p_str" to="StgValue_20" fromId="101" toId="20">
</dataflow>
<dataflow id="174" from="p_str" to="StgValue_20" fromId="101" toId="20">
</dataflow>
<dataflow id="175" from="p_str" to="StgValue_20" fromId="101" toId="20">
</dataflow>
<dataflow id="176" from="StgValue_98" to="StgValue_20" fromId="98" toId="20">
</dataflow>
<dataflow id="177" from="StgValue_98" to="StgValue_20" fromId="98" toId="20">
</dataflow>
<dataflow id="178" from="StgValue_98" to="StgValue_20" fromId="98" toId="20">
</dataflow>
<dataflow id="179" from="StgValue_98" to="StgValue_20" fromId="98" toId="20">
</dataflow>
<dataflow id="180" from="p_str" to="StgValue_20" fromId="101" toId="20">
</dataflow>
<dataflow id="181" from="p_str" to="StgValue_20" fromId="101" toId="20">
</dataflow>
<dataflow id="182" from="_ssdm_op_SpecInterface" to="StgValue_21" fromId="93" toId="21">
</dataflow>
<dataflow id="183" from="center_line_V" to="StgValue_21" fromId="61" toId="21">
</dataflow>
<dataflow id="184" from="p_str2" to="StgValue_21" fromId="96" toId="21">
</dataflow>
<dataflow id="185" from="StgValue_98" to="StgValue_21" fromId="98" toId="21">
</dataflow>
<dataflow id="186" from="StgValue_98" to="StgValue_21" fromId="98" toId="21">
</dataflow>
<dataflow id="187" from="p_str" to="StgValue_21" fromId="101" toId="21">
</dataflow>
<dataflow id="188" from="StgValue_98" to="StgValue_21" fromId="98" toId="21">
</dataflow>
<dataflow id="189" from="StgValue_98" to="StgValue_21" fromId="98" toId="21">
</dataflow>
<dataflow id="190" from="p_str" to="StgValue_21" fromId="101" toId="21">
</dataflow>
<dataflow id="191" from="p_str" to="StgValue_21" fromId="101" toId="21">
</dataflow>
<dataflow id="192" from="p_str" to="StgValue_21" fromId="101" toId="21">
</dataflow>
<dataflow id="193" from="StgValue_98" to="StgValue_21" fromId="98" toId="21">
</dataflow>
<dataflow id="194" from="StgValue_98" to="StgValue_21" fromId="98" toId="21">
</dataflow>
<dataflow id="195" from="StgValue_98" to="StgValue_21" fromId="98" toId="21">
</dataflow>
<dataflow id="196" from="StgValue_98" to="StgValue_21" fromId="98" toId="21">
</dataflow>
<dataflow id="197" from="p_str" to="StgValue_21" fromId="101" toId="21">
</dataflow>
<dataflow id="198" from="p_str" to="StgValue_21" fromId="101" toId="21">
</dataflow>
<dataflow id="199" from="y_V_read" to="tmp" fromId="14" toId="22">
</dataflow>
<dataflow id="201" from="StgValue_200" to="tmp" fromId="200" toId="22">
</dataflow>
<dataflow id="202" from="tmp" to="StgValue_23" fromId="22" toId="23">
</dataflow>
<dataflow id="203" from="x_V_read" to="tmp_1" fromId="15" toId="24">
</dataflow>
<dataflow id="205" from="StgValue_204" to="tmp_1" fromId="204" toId="24">
</dataflow>
<dataflow id="206" from="tmp_1" to="StgValue_25" fromId="24" toId="25">
</dataflow>
<dataflow id="207" from="right_read" to="not_right" fromId="12" toId="26">
</dataflow>
<dataflow id="209" from="StgValue_208" to="not_right" fromId="208" toId="26">
</dataflow>
<dataflow id="210" from="not_right" to="storemerge7_cast" fromId="26" toId="27">
</dataflow>
<dataflow id="212" from="StgValue_211" to="storemerge7_cast" fromId="211" toId="27">
</dataflow>
<dataflow id="214" from="StgValue_213" to="storemerge7_cast" fromId="213" toId="27">
</dataflow>
<dataflow id="216" from="_ssdm_op_Write.ap_none.i8P" to="StgValue_28" fromId="215" toId="28">
</dataflow>
<dataflow id="217" from="XY_Red_V" to="StgValue_28" fromId="58" toId="28">
</dataflow>
<dataflow id="218" from="storemerge7_cast" to="StgValue_28" fromId="27" toId="28">
</dataflow>
<dataflow id="219" from="_ssdm_op_Write.ap_none.i8P" to="StgValue_29" fromId="215" toId="29">
</dataflow>
<dataflow id="220" from="XY_Blue_V" to="StgValue_29" fromId="60" toId="29">
</dataflow>
<dataflow id="221" from="storemerge7_cast" to="StgValue_29" fromId="27" toId="29">
</dataflow>
<dataflow id="222" from="_ssdm_op_Write.ap_none.i8P" to="StgValue_30" fromId="215" toId="30">
</dataflow>
<dataflow id="223" from="XY_Green_V" to="StgValue_30" fromId="59" toId="30">
</dataflow>
<dataflow id="224" from="storemerge7_cast" to="StgValue_30" fromId="27" toId="30">
</dataflow>
<dataflow id="225" from="x_V_read" to="tmp_2" fromId="15" toId="32">
</dataflow>
<dataflow id="226" from="StgValue_204" to="tmp_2" fromId="204" toId="32">
</dataflow>
<dataflow id="227" from="tmp_2" to="StgValue_33" fromId="32" toId="33">
</dataflow>
<dataflow id="228" from="right_read" to="storemerge6" fromId="12" toId="34">
</dataflow>
<dataflow id="229" from="StgValue_211" to="storemerge6" fromId="211" toId="34">
</dataflow>
<dataflow id="230" from="StgValue_213" to="storemerge6" fromId="213" toId="34">
</dataflow>
<dataflow id="231" from="_ssdm_op_Write.ap_none.i8P" to="StgValue_35" fromId="215" toId="35">
</dataflow>
<dataflow id="232" from="XY_Red_V" to="StgValue_35" fromId="58" toId="35">
</dataflow>
<dataflow id="233" from="storemerge6" to="StgValue_35" fromId="34" toId="35">
</dataflow>
<dataflow id="234" from="_ssdm_op_Write.ap_none.i8P" to="StgValue_36" fromId="215" toId="36">
</dataflow>
<dataflow id="235" from="XY_Blue_V" to="StgValue_36" fromId="60" toId="36">
</dataflow>
<dataflow id="236" from="storemerge6" to="StgValue_36" fromId="34" toId="36">
</dataflow>
<dataflow id="237" from="_ssdm_op_Write.ap_none.i8P" to="StgValue_37" fromId="215" toId="37">
</dataflow>
<dataflow id="238" from="XY_Green_V" to="StgValue_37" fromId="59" toId="37">
</dataflow>
<dataflow id="239" from="storemerge6" to="StgValue_37" fromId="34" toId="37">
</dataflow>
<dataflow id="240" from="y_V_read" to="tmp_3" fromId="14" toId="40">
</dataflow>
<dataflow id="241" from="StgValue_200" to="tmp_3" fromId="200" toId="40">
</dataflow>
<dataflow id="242" from="tmp_3" to="StgValue_41" fromId="40" toId="41">
</dataflow>
<dataflow id="243" from="x_V_read" to="tmp_4_cast" fromId="15" toId="42">
</dataflow>
<dataflow id="244" from="tmp_4_cast" to="tmp_6" fromId="42" toId="43">
</dataflow>
<dataflow id="245" from="center_line_V_read" to="tmp_6" fromId="13" toId="43">
</dataflow>
<dataflow id="246" from="tmp_6" to="not_tmp_6" fromId="43" toId="44">
</dataflow>
<dataflow id="247" from="StgValue_208" to="not_tmp_6" fromId="208" toId="44">
</dataflow>
<dataflow id="248" from="not_tmp_6" to="storemerge5_cast" fromId="44" toId="45">
</dataflow>
<dataflow id="249" from="StgValue_211" to="storemerge5_cast" fromId="211" toId="45">
</dataflow>
<dataflow id="250" from="StgValue_213" to="storemerge5_cast" fromId="213" toId="45">
</dataflow>
<dataflow id="251" from="tmp_6" to="storemerge" fromId="43" toId="46">
</dataflow>
<dataflow id="252" from="StgValue_211" to="storemerge" fromId="211" toId="46">
</dataflow>
<dataflow id="253" from="StgValue_213" to="storemerge" fromId="213" toId="46">
</dataflow>
<dataflow id="254" from="_ssdm_op_Write.ap_none.i8P" to="StgValue_47" fromId="215" toId="47">
</dataflow>
<dataflow id="255" from="XY_Red_V" to="StgValue_47" fromId="58" toId="47">
</dataflow>
<dataflow id="256" from="storemerge5_cast" to="StgValue_47" fromId="45" toId="47">
</dataflow>
<dataflow id="257" from="_ssdm_op_Write.ap_none.i8P" to="StgValue_48" fromId="215" toId="48">
</dataflow>
<dataflow id="258" from="XY_Blue_V" to="StgValue_48" fromId="60" toId="48">
</dataflow>
<dataflow id="259" from="StgValue_213" to="StgValue_48" fromId="213" toId="48">
</dataflow>
<dataflow id="260" from="_ssdm_op_Write.ap_none.i8P" to="StgValue_49" fromId="215" toId="49">
</dataflow>
<dataflow id="261" from="XY_Green_V" to="StgValue_49" fromId="59" toId="49">
</dataflow>
<dataflow id="262" from="storemerge" to="StgValue_49" fromId="46" toId="49">
</dataflow>
<dataflow id="263" from="tmp" to="StgValue_1" fromId="22" toId="1">
</dataflow>
<dataflow id="264" from="tmp_1" to="StgValue_1" fromId="24" toId="1">
</dataflow>
<dataflow id="265" from="tmp" to="StgValue_2" fromId="22" toId="2">
</dataflow>
<dataflow id="266" from="tmp_2" to="StgValue_2" fromId="32" toId="2">
</dataflow>
<dataflow id="267" from="tmp_3" to="StgValue_2" fromId="40" toId="2">
</dataflow>
<dataflow id="268" from="tmp_3" to="StgValue_3" fromId="40" toId="3">
</dataflow>
</dataflows>


</stg>
